Metadata-Version: 2.4
Name: iflow-mcp_mcp-server-iceberg
Version: 0.1.0
Summary: MCP server for interacting with an Apache Iceberg catalog and data lake
Requires-Python: >=3.10
Requires-Dist: fsspec
Requires-Dist: mcp>=1.0.0
Requires-Dist: pyarrow>=14.0.1
Requires-Dist: pyiceberg>=0.5.1
Requires-Dist: python-dotenv
Requires-Dist: requests
Requires-Dist: s3fs
Requires-Dist: sqlparse>=0.4.4
